benchexec/__init__.py
benchexec/baseexecutor.py
benchexec/benchexec.py
benchexec/cgroups.py
benchexec/cgroupsv1.py
benchexec/cgroupsv2.py
benchexec/check_cgroups.py
benchexec/container.py
benchexec/containerexecutor.py
benchexec/containerized_tool.py
benchexec/filehierarchylimit.py
benchexec/filewriter.py
benchexec/intel_cpu_energy.py
benchexec/libc.py
benchexec/localexecution.py
benchexec/model.py
benchexec/oomhandler.py
benchexec/outputhandler.py
benchexec/pqos.py
benchexec/resources.py
benchexec/result.py
benchexec/runexecutor.py
benchexec/seccomp.py
benchexec/systeminfo.py
benchexec/test_analyze_run_result.py
benchexec/test_benchmark_definition.py
benchexec/test_cgroups.py
benchexec/test_core_assignment.py
benchexec/test_pqos.py
benchexec/test_result.py
benchexec/test_runexecutor.py
benchexec/test_tool_info.py
benchexec/test_util.py
benchexec/tooladapter.py
benchexec/util.py
benchexec/tablegenerator/__init__.py
benchexec/tablegenerator/columns.py
benchexec/tablegenerator/htmltable.py
benchexec/tablegenerator/statistics.py
benchexec/tablegenerator/statisticstex.py
benchexec/tablegenerator/test_columns.py
benchexec/tablegenerator/test_statvalue.py
benchexec/tablegenerator/test_util.py
benchexec/tablegenerator/util.py
benchexec/tablegenerator/react-table/build/main.min.css
benchexec/tablegenerator/react-table/build/main.min.js
benchexec/tablegenerator/react-table/build/vendors.min.css
benchexec/tablegenerator/react-table/build/vendors.min.js
benchexec/tools/__init__.py
benchexec/tools/abc.py
benchexec/tools/acsar.py
benchexec/tools/afltc.py
benchexec/tools/aise.py
benchexec/tools/aprove.py
benchexec/tools/avr.py
benchexec/tools/blast.py
benchexec/tools/brick.py
benchexec/tools/btor2c.py
benchexec/tools/btormc.py
benchexec/tools/bubaak.py
benchexec/tools/calculatepi.py
benchexec/tools/cascade.py
benchexec/tools/cbmc-path.py
benchexec/tools/cbmc.py
benchexec/tools/ceagle.py
benchexec/tools/cetfuzz.py
benchexec/tools/civl.py
benchexec/tools/cmaesfuzz.py
benchexec-3.33.dist-info/licenses/LICENSES/Apache-2.0.txt
benchexec-3.33.dist-info/licenses/LICENSES/BSD-3-Clause.txt
benchexec-3.33.dist-info/licenses/LICENSES/CC-BY-4.0.txt
benchexec-3.33.dist-info/licenses/LICENSES/ISC.txt
benchexec-3.33.dist-info/licenses/LICENSES/LicenseRef-BSD-3-Clause-CMU.txt
benchexec-3.33.dist-info/licenses/LICENSES/MIT.txt
benchexec-3.33.dist-info/METADATA
benchexec-3.33.dist-info/WHEEL
benchexec-3.33.dist-info/entry_points.txt
benchexec-3.33.dist-info/top_level.txt
benchexec-3.33.dist-info/zip-safe
benchexec-3.33.dist-info/RECORD
