Metadata-Version: 2.4
Name: BenchExec
Version: 3.33
Summary: A Framework for Reliable Benchmarking and Resource Measurement.
Author: Dirk Beyer
License: Apache-2.0 AND BSD-3-Clause AND CC-BY-4.0 AND MIT AND ISC AND LicenseRef-BSD-3-Clause-CMU
Project-URL: Homepage, https://github.com/sosy-lab/benchexec/
Project-URL: Documentation, https://github.com/sosy-lab/benchexec/blob/main/doc/INDEX.md
Project-URL: Changelog, https://github.com/sosy-lab/benchexec/blob/main/CHANGELOG.md
Project-URL: Issue Tracker, https://github.com/sosy-lab/benchexec/issues
Keywords: benchmarking,resource measurement
Platform: Linux
Classifier: Development Status :: 5 - Production/Stable
Classifier: Environment :: Console
Classifier: Intended Audience :: Science/Research
Classifier: License :: OSI Approved :: Apache Software License
Classifier: License :: OSI Approved :: BSD License
Classifier: License :: OSI Approved :: ISC License (ISCL)
Classifier: License :: OSI Approved :: MIT License
Classifier: Operating System :: POSIX :: Linux
Classifier: Programming Language :: Python :: 3 :: Only
Classifier: Topic :: System :: Benchmark
Requires-Python: >=3.10
License-File: LICENSES/Apache-2.0.txt
License-File: LICENSES/BSD-3-Clause.txt
License-File: LICENSES/CC-BY-4.0.txt
License-File: LICENSES/ISC.txt
License-File: LICENSES/LicenseRef-BSD-3-Clause-CMU.txt
License-File: LICENSES/MIT.txt
Requires-Dist: PyYAML>=3.12
Provides-Extra: dev
Requires-Dist: lxml; extra == "dev"
Requires-Dist: pytest; extra == "dev"
Requires-Dist: pystemd>=0.7.0; platform_system != "Windows" and extra == "dev"
Provides-Extra: systemd
Requires-Dist: pystemd>=0.7.0; platform_system != "Windows" and extra == "systemd"
Dynamic: license-file
